muar/__init__.py
muar/augmentations.py
muar/loss.py
muar/transform_lists.py
muar/utils.py
muar/augmentations/AlbumentationsRandAugment.py
muar/augmentations/BatchRandAugment.py
muar/augmentations/MuAugment.py
muar/augmentations/__init__.py
muar/loss/MixUpCrossEntropy.py
muar/loss/__init__.py
muar/transform_lists/__init__.py
muar/transform_lists/augmentations_list.py
muar/transform_lists/kornia_list.py
muar/utils/__init__.py
muar/utils/show_augmented_grid.py
muar/utils/tensor2pil.py
MuarAugment-1.1.1.dist-info/LICENSE
MuarAugment-1.1.1.dist-info/METADATA
MuarAugment-1.1.1.dist-info/WHEEL
MuarAugment-1.1.1.dist-info/top_level.txt
MuarAugment-1.1.1.dist-info/RECORD
