Metadata-Version: 2.1
Name: MuarAugment
Version: 1.1.1
Summary: State-of-the-art data augmentation search algorithms in PyTorch
Home-page: https://github.com/adam-mehdi/MuarAugment
Author: Adam Mehdi
Author-email: amehdi.25@dartmouth.edu
License: UNKNOWN
Platform: UNKNOWN
Requires-Dist: pytorch-lightning
Requires-Dist: kornia
